legislice/__init__.py
legislice/citations.py
legislice/download.py
legislice/enactments.py
legislice/groups.py
legislice/mock_clients.py
legislice/name_index.py
legislice/py.typed
legislice/schemas.py
legislice/types.py
legislice/yaml_schemas.py
tests/__init__.py
tests/conftest.py
tests/test_citations.py
tests/test_download.py
tests/test_enactments.py
tests/test_groups.py
tests/test_load_json.py
tests/test_schema.py
legislice-0.8.1.dist-info/METADATA
legislice-0.8.1.dist-info/WHEEL
legislice-0.8.1.dist-info/top_level.txt
legislice-0.8.1.dist-info/RECORD
