Metadata-Version: 2.2
Name: legislice
Version: 0.8.1
Summary: API client for fetching and comparing passages from legislation
Home-page: https://github.com/mscarey/legislice
Author: Matt Carey
Author-email: matt@authorityspoke.com
Project-URL: Bug Tracker, https://github.com/mscarey/legislice/issues
Project-URL: Documentation, https://legislice.readthedocs.io/en/latest/
Classifier: Development Status :: 4 - Beta
Classifier: Intended Audience :: Legal Industry
Classifier: License :: Free To Use But Restricted
Classifier: Programming Language :: Python :: 3.11
Classifier: Programming Language :: Python :: 3.12
Classifier: Operating System :: OS Independent
Classifier: Natural Language :: English
Classifier: Topic :: Sociology :: History
Requires-Python: >=3.11
